[{"outputFileName":"Scripts/Accordion.min.js","inputFiles":["Scripts/Accordion.js"]},{"outputFileName":"Scripts/AjaxFileUpload.min.js","inputFiles":["Scripts/AjaxFileUpload.js"]},{"outputFileName":"Scripts/AlwaysVisibleControl.min.js","inputFiles":["Scripts/AlwaysVisibleControl.js"]},{"outputFileName":"Scripts/Animation.min.js","inputFiles":["Scripts/Animation.js"]},{"outputFileName":"Scripts/AnimationScripts.min.js","inputFiles":["Scripts/AnimationScripts.js"]},{"outputFileName":"Scripts/AreaChart.min.js","inputFiles":["Scripts/AreaChart.js"]},{"outputFileName":"Scripts/AsyncFileUpload.min.js","inputFiles":["Scripts/AsyncFileUpload.js"]},{"outputFileName":"Scripts/AutoComplete.min.js","inputFiles":["Scripts/AutoComplete.js"]},{"outputFileName":"Scripts/BalloonPopup.min.js","inputFiles":["Scripts/BalloonPopup.js"]},{"outputFileName":"Scripts/BarChart.min.js","inputFiles":["Scripts/BarChart.js"]},{"outputFileName":"Scripts/BaseScripts.min.js","inputFiles":["Scripts/BaseScripts.js"]},{"outputFileName":"Scripts/BubbleChart.min.js","inputFiles":["Scripts/BubbleChart.js"]},{"outputFileName":"Scripts/Calendar.min.js","inputFiles":["Scripts/Calendar.js"]},{"outputFileName":"Scripts/CascadingDropDown.min.js","inputFiles":["Scripts/CascadingDropDown.js"]},{"outputFileName":"Scripts/CollapsiblePanel.min.js","inputFiles":["Scripts/CollapsiblePanel.js"]},{"outputFileName":"Scripts/ColorPicker.min.js","inputFiles":["Scripts/ColorPicker.js"]},{"outputFileName":"Scripts/ComboBox.min.js","inputFiles":["Scripts/ComboBox.js"]},{"outputFileName":"Scripts/Common.min.js","inputFiles":["Scripts/Common.js"]},{"outputFileName":"Scripts/ComponentSet.min.js","inputFiles":["Scripts/ComponentSet.js"]},{"outputFileName":"Scripts/ConfirmButton.min.js","inputFiles":["Scripts/ConfirmButton.js"]},{"outputFileName":"Scripts/DraggableListItem.min.js","inputFiles":["Scripts/DraggableListItem.js"]},{"outputFileName":"Scripts/DropDown.min.js","inputFiles":["Scripts/DropDown.js"]},{"outputFileName":"Scripts/DropShadow.min.js","inputFiles":["Scripts/DropShadow.js"]},{"outputFileName":"Scripts/DropWatcher.min.js","inputFiles":["Scripts/DropWatcher.js"]},{"outputFileName":"Scripts/DynamicPopulate.min.js","inputFiles":["Scripts/DynamicPopulate.js"]},{"outputFileName":"Scripts/FilteredTextBox.min.js","inputFiles":["Scripts/FilteredTextBox.js"]},{"outputFileName":"Scripts/FloatingBehavior.min.js","inputFiles":["Scripts/FloatingBehavior.js"]},{"outputFileName":"Scripts/Hover.min.js","inputFiles":["Scripts/Hover.js"]},{"outputFileName":"Scripts/HoverMenu.min.js","inputFiles":["Scripts/HoverMenu.js"]},{"outputFileName":"Scripts/HtmlEditorExtender.min.js","inputFiles":["Scripts/HtmlEditorExtender.js"]},{"outputFileName":"Scripts/LineChart.min.js","inputFiles":["Scripts/LineChart.js"]},{"outputFileName":"Scripts/ListSearch.min.js","inputFiles":["Scripts/ListSearch.js"]},{"outputFileName":"Scripts/MaskedEdit.min.js","inputFiles":["Scripts/MaskedEdit.js"]},{"outputFileName":"Scripts/MaskedEditValidator.min.js","inputFiles":["Scripts/MaskedEditValidator.js"]},{"outputFileName":"Scripts/ModalPopup.min.js","inputFiles":["Scripts/ModalPopup.js"]},{"outputFileName":"Scripts/MultiHandleSlider.min.js","inputFiles":["Scripts/MultiHandleSlider.js"]},{"outputFileName":"Scripts/MutuallyExclusiveCheckBox.min.js","inputFiles":["Scripts/MutuallyExclusiveCheckBox.js"]},{"outputFileName":"Scripts/NoBot.min.js","inputFiles":["Scripts/NoBot.js"]},{"outputFileName":"Scripts/NumericUpDown.min.js","inputFiles":["Scripts/NumericUpDown.js"]},{"outputFileName":"Scripts/PagingBulletedList.min.js","inputFiles":["Scripts/PagingBulletedList.js"]},{"outputFileName":"Scripts/PasswordStrength.min.js","inputFiles":["Scripts/PasswordStrength.js"]},{"outputFileName":"Scripts/PieChart.min.js","inputFiles":["Scripts/PieChart.js"]},{"outputFileName":"Scripts/Popup.min.js","inputFiles":["Scripts/Popup.js"]},{"outputFileName":"Scripts/PopupControl.min.js","inputFiles":["Scripts/PopupControl.js"]},{"outputFileName":"Scripts/Rating.min.js","inputFiles":["Scripts/Rating.js"]},{"outputFileName":"Scripts/ResizableControl.min.js","inputFiles":["Scripts/ResizableControl.js"]},{"outputFileName":"Scripts/RoundedCorners.min.js","inputFiles":["Scripts/RoundedCorners.js"]},{"outputFileName":"Scripts/Seadragon.min.js","inputFiles":["Scripts/Seadragon.js"]},{"outputFileName":"Scripts/Slider.min.js","inputFiles":["Scripts/Slider.js"]},{"outputFileName":"Scripts/SlideShow.min.js","inputFiles":["Scripts/SlideShow.js"]},{"outputFileName":"Scripts/Tabs.min.js","inputFiles":["Scripts/Tabs.js"]},{"outputFileName":"Scripts/TextBoxWatermark.min.js","inputFiles":["Scripts/TextBoxWatermark.js"]},{"outputFileName":"Scripts/ToggleButton.min.js","inputFiles":["Scripts/ToggleButton.js"]},{"outputFileName":"Scripts/UpdatePanelAnimation.min.js","inputFiles":["Scripts/UpdatePanelAnimation.js"]},{"outputFileName":"Scripts/ValidatorCallout.min.js","inputFiles":["Scripts/ValidatorCallout.js"]},{"outputFileName":"Scripts/Localization/Resources.min.js","inputFiles":["Scripts/Localization/Resources.js"]},{"outputFileName":"Scripts/Localization/Resources_ar.min.js","inputFiles":["Scripts/Localization/Resources_ar.js"]},{"outputFileName":"Scripts/Localization/Resources_cs.min.js","inputFiles":["Scripts/Localization/Resources_cs.js"]},{"outputFileName":"Scripts/Localization/Resources_de.min.js","inputFiles":["Scripts/Localization/Resources_de.js"]},{"outputFileName":"Scripts/Localization/Resources_es.min.js","inputFiles":["Scripts/Localization/Resources_es.js"]},{"outputFileName":"Scripts/Localization/Resources_fr.min.js","inputFiles":["Scripts/Localization/Resources_fr.js"]},{"outputFileName":"Scripts/Localization/Resources_he.min.js","inputFiles":["Scripts/Localization/Resources_he.js"]},{"outputFileName":"Scripts/Localization/Resources_hi.min.js","inputFiles":["Scripts/Localization/Resources_hi.js"]},{"outputFileName":"Scripts/Localization/Resources_it.min.js","inputFiles":["Scripts/Localization/Resources_it.js"]},{"outputFileName":"Scripts/Localization/Resources_ja.min.js","inputFiles":["Scripts/Localization/Resources_ja.js"]},{"outputFileName":"Scripts/Localization/Resources_ko.min.js","inputFiles":["Scripts/Localization/Resources_ko.js"]},{"outputFileName":"Scripts/Localization/Resources_nl.min.js","inputFiles":["Scripts/Localization/Resources_nl.js"]},{"outputFileName":"Scripts/Localization/Resources_pl.min.js","inputFiles":["Scripts/Localization/Resources_pl.js"]},{"outputFileName":"Scripts/Localization/Resources_pt.min.js","inputFiles":["Scripts/Localization/Resources_pt.js"]},{"outputFileName":"Scripts/Localization/Resources_ru.min.js","inputFiles":["Scripts/Localization/Resources_ru.js"]},{"outputFileName":"Scripts/Localization/Resources_tr.min.js","inputFiles":["Scripts/Localization/Resources_tr.js"]}]